{
  "isStruct": false,
  "key": [
    "id"
  ],
  "semantic": "inter| |date",
  "name": "mettingEvent",
  "version": "",
  "caption": "Встреча",
  "ancestor": null,
  "container": null,
  "creationTracker": "",
  "changeTracker": "",
  "history": 0,
  "journaling": false,
  "compositeIndexes": null,
  "properties": [
    {
      "orderNumber": 10,
      "name": "id",
      "caption": "Идентификатор",
      "type": 12,
      "size": null,
      "decimals": 0,
      "allowedFileTypes": null,
      "maxFileCount": 0,
      "nullable": false,
      "readonly": true,
      "indexed": false,
      "unique": true,
      "autoassigned": true,
      "hint": null,
      "defaultValue": null,
      "refClass": "",
      "itemsClass": "",
      "backRef": "",
      "backColl": "",
      "binding": "",
      "semantic": null,
      "selConditions": [],
      "selSorting": [],
      "selectionProvider": null,
      "indexSearch": false,
      "eagerLoading": false,
      "formula": null
    },
    {
      "orderNumber": 20,
      "name": "inter",
      "caption": "Тема встречи",
      "type": 0,
      "size": null,
      "decimals": 0,
      "allowedFileTypes": null,
      "maxFileCount": 0,
      "nullable": true,
      "readonly": false,
      "indexed": false,
      "unique": false,
      "autoassigned": false,
      "hint": null,
      "defaultValue": null,
      "refClass": "",
      "itemsClass": "",
      "backRef": "",
      "backColl": "",
      "binding": "",
      "semantic": null,
      "selConditions": [],
      "selSorting": [],
      "selectionProvider": null,
      "indexSearch": false,
      "eagerLoading": false,
      "formula": null
    },
    {
      "orderNumber": 30,
      "name": "date",
      "caption": "Дата",
      "type": 9,
      "size": null,
      "decimals": 0,
      "allowedFileTypes": null,
      "maxFileCount": 0,
      "nullable": true,
      "readonly": false,
      "indexed": false,
      "unique": false,
      "autoassigned": false,
      "hint": null,
      "defaultValue": null,
      "refClass": "",
      "itemsClass": "",
      "backRef": "",
      "backColl": "",
      "binding": "",
      "semantic": null,
      "selConditions": [],
      "selSorting": [],
      "selectionProvider": null,
      "indexSearch": false,
      "eagerLoading": false,
      "formula": null
    },
    {
      "orderNumber": 40,
      "name": "person",
      "caption": "Персона",
      "type": 13,
      "size": null,
      "decimals": 0,
      "allowedFileTypes": null,
      "maxFileCount": 0,
      "nullable": true,
      "readonly": false,
      "indexed": false,
      "unique": false,
      "autoassigned": false,
      "hint": null,
      "defaultValue": null,
      "refClass": "person",
      "itemsClass": "",
      "backRef": "",
      "backColl": "",
      "binding": "",
      "semantic": null,
      "selConditions": [],
      "selSorting": [],
      "selectionProvider": null,
      "indexSearch": false,
      "eagerLoading": false,
      "formula": null
    },
    {
      "orderNumber": 50,
      "name": "worker",
      "caption": "Сотрудник",
      "type": 13,
      "size": null,
      "decimals": 0,
      "allowedFileTypes": null,
      "maxFileCount": 0,
      "nullable": true,
      "readonly": false,
      "indexed": false,
      "unique": false,
      "autoassigned": false,
      "hint": null,
      "defaultValue": null,
      "refClass": "worker",
      "itemsClass": "",
      "backRef": "",
      "backColl": "",
      "binding": "",
      "semantic": null,
      "selConditions": [],
      "selSorting": [],
      "selectionProvider": null,
      "indexSearch": false,
      "eagerLoading": false,
      "formula": null
    },
    {
      "orderNumber": 60,
      "name": "organiz",
      "caption": "Организация",
      "type": 13,
      "size": null,
      "decimals": 0,
      "allowedFileTypes": null,
      "maxFileCount": 0,
      "nullable": true,
      "readonly": false,
      "indexed": false,
      "unique": false,
      "autoassigned": false,
      "hint": null,
      "defaultValue": null,
      "refClass": "organization",
      "itemsClass": "",
      "backRef": "",
      "backColl": "",
      "binding": "",
      "semantic": null,
      "selConditions": [],
      "selSorting": [],
      "selectionProvider": null,
      "indexSearch": false,
      "eagerLoading": false,
      "formula": null
    },
    {
      "orderNumber": 70,
      "name": "event",
      "caption": "Событие",
      "type": 13,
      "size": null,
      "decimals": 0,
      "allowedFileTypes": null,
      "maxFileCount": 0,
      "nullable": true,
      "readonly": false,
      "indexed": false,
      "unique": false,
      "autoassigned": false,
      "hint": null,
      "defaultValue": null,
      "refClass": "event",
      "itemsClass": "",
      "backRef": "",
      "backColl": "",
      "binding": "",
      "semantic": null,
      "selConditions": [],
      "selSorting": [],
      "selectionProvider": null,
      "indexSearch": false,
      "eagerLoading": false,
      "formula": null
    }
  ],
  "metaVersion": "2.0.61.15690"
}