{
  "support": "RPGU (SAKHALIN)",
  "taskClassification": null,
  "name": "ПЕРЕНАПРАВЛЕНИЕ НА ГОСУСЛУГИ",
  "id": "3f2d4820-d0cf-11e8-9796-f574ea641f27",
  "endTaskClassification": false,
  "needRefactoringScenario": false,
  "_class": "supportScenario@crm",
  "_classVer": "",
  "_creator": "jeneva@local",
  "scenario": "<i>Этот сценарий зачитываем, если звонит пользователь, которому нужна консультация по услугам, которые оказываются на портале Госуслуг: запись на прием к врачу, (требуется дополнять список таких услуг, чтобы сразу иметь возможность правильно направить заявителя)<br><br></i><b>Текст оператора:</b><i><br></i><br>Данные услуги предоставляются федеральным сайтом Госуслуги. Мы в этом случае выступаем как дружественный сайт, который разместил на своих страницах полезную и нужную информацию для своих посетителей<i>. </i>Если при получении этих услуг вы столкнулись с проблемами или ошибками, мы рекомендуем обратиться в тех.поддержку 8-800-100-70-10<br>",
  "_editor": "jeneva@local",
  "___workflowStatus": {}
}